README.md
setup.py
zap_report_formatter/__init__.py
zap_report_formatter/zap_report_formatter.py
zap_report_formatter.egg-info/PKG-INFO
zap_report_formatter.egg-info/SOURCES.txt
zap_report_formatter.egg-info/dependency_links.txt
zap_report_formatter.egg-info/top_level.txt