Metadata-Version: 2.1
Name: zap-report-formatter
Version: 0.0.2
Summary: Takes in OWASP ZAP json reports and produces whitelisted xml reports for Jenkins Junit plugin.
Home-page: https://github.com/wongherlung/zap_report_formatter
Author: Wong Her Laang
Author-email: wongherlung@gmail.com
License: UNKNOWN
Platform: UNKNOWN
Classifier: Programming Language :: Python :: 2.7
Classifier: License :: OSI Approved :: MIT License
Classifier: Operating System :: OS Independent
